pymtl3/__init__.py
pymtl3/version.py
pymtl3/datatypes/PythonBits.py
pymtl3/datatypes/__init__.py
pymtl3/datatypes/bits_import.py
pymtl3/datatypes/bitstructs.py
pymtl3/datatypes/helpers.py
pymtl3/datatypes/strategies.py
pymtl3/datatypes/test/__init__.py
pymtl3/datatypes/test/bits_test.py
pymtl3/datatypes/test/bitstructs_test.py
pymtl3/datatypes/test/helpers_test.py
pymtl3/datatypes/test/strategies_test.py
pymtl3/dsl/AstHelper.py
pymtl3/dsl/Component.py
pymtl3/dsl/ComponentLevel1.py
pymtl3/dsl/ComponentLevel2.py
pymtl3/dsl/ComponentLevel3.py
pymtl3/dsl/ComponentLevel4.py
pymtl3/dsl/ComponentLevel5.py
pymtl3/dsl/ComponentLevel6.py
pymtl3/dsl/ComponentLevel7.py
pymtl3/dsl/Connectable.py
pymtl3/dsl/ConstraintTypes.py
pymtl3/dsl/MetadataKey.py
pymtl3/dsl/NamedObject.py
pymtl3/dsl/Placeholder.py
pymtl3/dsl/__init__.py
pymtl3/dsl/errors.py
pymtl3/dsl/test/ComponentAPI_test.py
pymtl3/dsl/test/ComponentLevel1_test.py
pymtl3/dsl/test/ComponentLevel2_test.py
pymtl3/dsl/test/ComponentLevel3_test.py
pymtl3/dsl/test/ComponentLevel4_test.py
pymtl3/dsl/test/ComponentLevel5_test.py
pymtl3/dsl/test/ComponentLevel6_test.py
pymtl3/dsl/test/DataStruct_test.py
pymtl3/dsl/test/Interface_test.py
pymtl3/dsl/test/NamedObject_test.py
pymtl3/dsl/test/Placeholder_test.py
pymtl3/dsl/test/PortCheck_test.py
pymtl3/dsl/test/Slicing_test.py
pymtl3/dsl/test/__init__.py
pymtl3/dsl/test/set_param_test.py
pymtl3/dsl/test/sim_utils.py
pymtl3/examples/__init__.py
pymtl3/examples/ex00_quickstart/FullAdder.py
pymtl3/examples/ex00_quickstart/RegIncr.py
pymtl3/examples/ex00_quickstart/__init__.py
pymtl3/extra/__init__.py
pymtl3/extra/clone_deepcopy.py
pymtl3/extra/pypy/__init__.py
pymtl3/extra/pypy/custom_exec.py
pymtl3/extra/pypy/fast_bytearray_funcs.py
pymtl3/passes/BasePass.py
pymtl3/passes/PassConfigs.py
pymtl3/passes/PassGroups.py
pymtl3/passes/PlaceholderConfigs.py
pymtl3/passes/PlaceholderPass.py
pymtl3/passes/__init__.py
pymtl3/passes/errors.py
pymtl3/passes/adhoc_transform/AddDebugSignalPass.py
pymtl3-3.1.16.dist-info/LICENSE
pymtl3-3.1.16.dist-info/METADATA
pymtl3-3.1.16.dist-info/WHEEL
pymtl3-3.1.16.dist-info/entry_points.txt
pymtl3-3.1.16.dist-info/top_level.txt
pymtl3-3.1.16.dist-info/RECORD
