Metadata-Version: 2.1
Name: pymtl3
Version: 3.1.16
Summary: PyMTL 3 (Mamba): A Python-based hardware generation, simulation, and verification framework
Home-page: https://github.com/pymtl/pymtl3
Author: Batten Research Group
Author-email: brg-pymtl@csl.cornell.edu
License: BSD
Platform: UNKNOWN
Classifier: Development Status :: 4 - Beta
Classifier: License :: OSI Approved :: BSD License
Classifier: Programming Language :: Python :: 3 :: Only
Classifier: Operating System :: MacOS :: MacOS X
Classifier: Operating System :: POSIX :: Linux
Classifier: Topic :: Scientific/Engineering :: Electronic Design Automation (EDA)
Requires-Python: >=3.6
